la_catch/__init__.py
la_catch/utility.py
la_catch-0.0.6.dist-info/WHEEL
la_catch-0.0.6.dist-info/METADATA
la_catch-0.0.6.dist-info/license_files/LICENSE
la_catch-0.0.6.dist-info/RECORD
