Metadata-Version: 2.1
Name: la-catch
Version: 0.0.6
Summary: Decorator to map exception to functions
License: MIT
Keywords: decorator,exception,catch
Author-email: thiagola92 <thiagola92@gmail.com>
Requires-Python: >=3.10
Classifier: License :: OSI Approved :: MIT License
Classifier: Operating System :: OS Independent
Classifier: Programming Language :: Python :: 3.10
Project-URL: repository, https://github.com/thiagola92/la-catch
